[
	{
		"id": 1,
		"first_name": "Corabella",
		"last_name": "Goves",
		"email": "cgoves0@unblog.fr",
		"gender": "Female",
		"address": "99 Fremont Drive"
	},
	{
		"id": 2,
		"first_name": "Lionel",
		"last_name": "Sutter",
		"email": "lsutter1@japanpost.jp",
		"gender": "Non-binary",
		"address": "1 Lake View Park"
	},
	{
		"id": 3,
		"first_name": "Ben",
		"last_name": "Cullity",
		"email": "bcullity2@pagesperso-orange.fr",
		"gender": "Male",
		"address": "38 Kinsman Trail"
	},
	{
		"id": 4,
		"first_name": "Cally",
		"last_name": "McNelis",
		"email": "cmcnelis3@pagesperso-orange.fr",
		"gender": "Female",
		"address": "66 Blue Bill Park Trail"
	},
	{
		"id": 5,
		"first_name": "Rosalyn",
		"last_name": "Sivill",
		"email": "rsivill4@lulu.com",
		"gender": "Female",
		"address": "67772 Del Sol Plaza"
	},
	{
		"id": 6,
		"first_name": "Chan",
		"last_name": "Tesseyman",
		"email": "ctesseyman5@soundcloud.com",
		"gender": "Male",
		"address": "2208 Lien Alley"
	},
	{
		"id": 7,
		"first_name": "Zelma",
		"last_name": "Partleton",
		"email": "zpartleton6@imdb.com",
		"gender": "Female",
		"address": "1510 Lukken Park"
	},
	{
		"id": 8,
		"first_name": "Les",
		"last_name": "Bantham",
		"email": "lbantham7@wisc.edu",
		"gender": "Male",
		"address": "75 Utah Court"
	},
	{
		"id": 9,
		"first_name": "Che",
		"last_name": "Flaxon",
		"email": "cflaxon8@phoca.cz",
		"gender": "Male",
		"address": "39127 Oxford Alley"
	},
	{
		"id": 10,
		"first_name": "Liane",
		"last_name": "Cuff",
		"email": "lcuff9@google.es",
		"gender": "Female",
		"address": "805 Rieder Terrace"
	},
	{
		"id": 11,
		"first_name": "Rochella",
		"last_name": "Tarbin",
		"email": "rtarbina@icq.com",
		"gender": "Female",
		"address": "07 Ruskin Avenue"
	},
	{
		"id": 12,
		"first_name": "Jeffie",
		"last_name": "Beeble",
		"email": "jbeebleb@epa.gov",
		"gender": "Male",
		"address": "6 Buell Terrace"
	},
	{
		"id": 13,
		"first_name": "Fred",
		"last_name": "Amis",
		"email": "famisc@utexas.edu",
		"gender": "Female",
		"address": "2329 Bay Hill"
	},
	{
		"id": 14,
		"first_name": "Pamelina",
		"last_name": "Liley",
		"email": "plileyd@163.com",
		"gender": "Genderqueer",
		"address": "7938 Parkside Terrace"
	},
	{
		"id": 15,
		"first_name": "Milty",
		"last_name": "Itzcak",
		"email": "mitzcake@dedecms.com",
		"gender": "Male",
		"address": "97 Butterfield Place"
	},
	{
		"id": 16,
		"first_name": "Dukie",
		"last_name": "Davidovitz",
		"email": "ddavidovitzf@qq.com",
		"gender": "Male",
		"address": "21 Briar Crest Place"
	},
	{
		"id": 17,
		"first_name": "Shaughn",
		"last_name": "Hassey",
		"email": "shasseyg@plala.or.jp",
		"gender": "Male",
		"address": "226 Rieder Center"
	},
	{
		"id": 18,
		"first_name": "Barbe",
		"last_name": "Perse",
		"email": "bperseh@odnoklassniki.ru",
		"gender": "Female",
		"address": "59 Heath Pass"
	},
	{
		"id": 19,
		"first_name": "Mattie",
		"last_name": "Esberger",
		"email": "mesbergeri@ftc.gov",
		"gender": "Male",
		"address": "50 Hovde Plaza"
	},
	{
		"id": 20,
		"first_name": "Ilario",
		"last_name": "Schruurs",
		"email": "ischruursj@plala.or.jp",
		"gender": "Male",
		"address": "22 Clemons Terrace"
	},
	{
		"id": 21,
		"first_name": "Gregoire",
		"last_name": "Schreiner",
		"email": "gschreinerk@yandex.ru",
		"gender": "Male",
		"address": "7946 Pennsylvania Avenue"
	},
	{
		"id": 22,
		"first_name": "Noni",
		"last_name": "Derricoat",
		"email": "nderricoatl@phpbb.com",
		"gender": "Female",
		"address": "11288 Nova Court"
	},
	{
		"id": 23,
		"first_name": "Nan",
		"last_name": "Wheelan",
		"email": "nwheelanm@cnet.com",
		"gender": "Female",
		"address": "76 Prairieview Avenue"
	},
	{
		"id": 24,
		"first_name": "Darsey",
		"last_name": "Gallally",
		"email": "dgallallyn@ebay.com",
		"gender": "Female",
		"address": "4322 Bartelt Plaza"
	},
	{
		"id": 25,
		"first_name": "Christal",
		"last_name": "Faulkner",
		"email": "cfaulknero@comsenz.com",
		"gender": "Female",
		"address": "9 Eagan Terrace"
	},
	{
		"id": 26,
		"first_name": "Gay",
		"last_name": "Bowery",
		"email": "gboweryp@deliciousdays.com",
		"gender": "Female",
		"address": "1041 Fulton Court"
	},
	{
		"id": 27,
		"first_name": "Nady",
		"last_name": "Carlucci",
		"email": "ncarlucciq@chronoengine.com",
		"gender": "Female",
		"address": "199 Summerview Parkway"
	},
	{
		"id": 28,
		"first_name": "Brinna",
		"last_name": "Imlacke",
		"email": "bimlacker@slate.com",
		"gender": "Female",
		"address": "46560 Jenna Point"
	},
	{
		"id": 29,
		"first_name": "Almeda",
		"last_name": "Haslewood",
		"email": "ahaslewoods@indiegogo.com",
		"gender": "Female",
		"address": "3 Doe Crossing Street"
	},
	{
		"id": 30,
		"first_name": "Lay",
		"last_name": "Hurrell",
		"email": "lhurrellt@google.nl",
		"gender": "Male",
		"address": "732 Cambridge Junction"
	},
	{
		"id": 31,
		"first_name": "Alvan",
		"last_name": "Dearing",
		"email": "adearingu@cdbaby.com",
		"gender": "Male",
		"address": "49 School Drive"
	},
	{
		"id": 32,
		"first_name": "Randell",
		"last_name": "Baddow",
		"email": "rbaddowv@example.com",
		"gender": "Male",
		"address": "41 Warner Parkway"
	},
	{
		"id": 33,
		"first_name": "Christie",
		"last_name": "Brinicombe",
		"email": "cbrinicombew@wix.com",
		"gender": "Female",
		"address": "97 Arizona Street"
	},
	{
		"id": 34,
		"first_name": "Lanie",
		"last_name": "Alfwy",
		"email": "lalfwyx@baidu.com",
		"gender": "Female",
		"address": "13303 Derek Street"
	},
	{
		"id": 35,
		"first_name": "Joelle",
		"last_name": "Skin",
		"email": "jskiny@harvard.edu",
		"gender": "Female",
		"address": "516 Bellgrove Hill"
	},
	{
		"id": 36,
		"first_name": "Mary",
		"last_name": "Jeffers",
		"email": "mjeffersz@google.cn",
		"gender": "Female",
		"address": "9989 Continental Circle"
	},
	{
		"id": 37,
		"first_name": "Simone",
		"last_name": "Slemmonds",
		"email": "sslemmonds10@geocities.com",
		"gender": "Female",
		"address": "33 South Avenue"
	},
	{
		"id": 38,
		"first_name": "Kim",
		"last_name": "Woodhams",
		"email": "kwoodhams11@yellowbook.com",
		"gender": "Male",
		"address": "73780 Valley Edge Parkway"
	},
	{
		"id": 39,
		"first_name": "Seline",
		"last_name": "Corker",
		"email": "scorker12@squarespace.com",
		"gender": "Female",
		"address": "30966 Dorton Drive"
	},
	{
		"id": 40,
		"first_name": "Padgett",
		"last_name": "Gresswood",
		"email": "pgresswood13@myspace.com",
		"gender": "Male",
		"address": "75708 Fieldstone Park"
	},
	{
		"id": 41,
		"first_name": "Davie",
		"last_name": "MacConnell",
		"email": "dmacconnell14@ehow.com",
		"gender": "Non-binary",
		"address": "231 Scott Place"
	},
	{
		"id": 42,
		"first_name": "Lonna",
		"last_name": "Virgin",
		"email": "lvirgin15@baidu.com",
		"gender": "Female",
		"address": "08163 Larry Parkway"
	},
	{
		"id": 43,
		"first_name": "Gunther",
		"last_name": "Suttling",
		"email": "gsuttling16@paypal.com",
		"gender": "Male",
		"address": "3 Swallow Point"
	},
	{
		"id": 44,
		"first_name": "Melody",
		"last_name": "Domke",
		"email": "mdomke17@disqus.com",
		"gender": "Female",
		"address": "6612 Lakeland Court"
	},
	{
		"id": 45,
		"first_name": "Jule",
		"last_name": "Greedyer",
		"email": "jgreedyer18@netlog.com",
		"gender": "Male",
		"address": "80859 David Parkway"
	},
	{
		"id": 46,
		"first_name": "Friedrich",
		"last_name": "Longshaw",
		"email": "flongshaw19@mac.com",
		"gender": "Male",
		"address": "220 5th Avenue"
	},
	{
		"id": 47,
		"first_name": "Raye",
		"last_name": "Gyrgorcewicx",
		"email": "rgyrgorcewicx1a@marriott.com",
		"gender": "Female",
		"address": "024 Onsgard Street"
	},
	{
		"id": 48,
		"first_name": "Samson",
		"last_name": "Summerside",
		"email": "ssummerside1b@tinypic.com",
		"gender": "Male",
		"address": "853 Nova Junction"
	},
	{
		"id": 49,
		"first_name": "Alejandro",
		"last_name": "Sommerling",
		"email": "asommerling1c@nhs.uk",
		"gender": "Male",
		"address": "168 Packers Park"
	},
	{
		"id": 50,
		"first_name": "Bonita",
		"last_name": "Copson",
		"email": "bcopson1d@home.pl",
		"gender": "Female",
		"address": "6 Wayridge Circle"
	},
	{
		"id": 51,
		"first_name": "Fredi",
		"last_name": "Pullan",
		"email": "fpullan1e@ebay.co.uk",
		"gender": "Female",
		"address": "27 Comanche Lane"
	},
	{
		"id": 52,
		"first_name": "Ninnette",
		"last_name": "Munson",
		"email": "nmunson1f@gnu.org",
		"gender": "Genderfluid",
		"address": "55993 Northland Junction"
	},
	{
		"id": 53,
		"first_name": "Ado",
		"last_name": "Simenet",
		"email": "asimenet1g@google.ru",
		"gender": "Male",
		"address": "947 Swallow Drive"
	},
	{
		"id": 54,
		"first_name": "Quintina",
		"last_name": "Joder",
		"email": "qjoder1h@desdev.cn",
		"gender": "Female",
		"address": "61 Cordelia Circle"
	},
	{
		"id": 55,
		"first_name": "Guthrey",
		"last_name": "Pennetti",
		"email": "gpennetti1i@addthis.com",
		"gender": "Male",
		"address": "01661 Northfield Lane"
	},
	{
		"id": 56,
		"first_name": "Evaleen",
		"last_name": "Dessaur",
		"email": "edessaur1j@apache.org",
		"gender": "Polygender",
		"address": "81884 Claremont Place"
	},
	{
		"id": 57,
		"first_name": "Ferguson",
		"last_name": "Hugin",
		"email": "fhugin1k@indiegogo.com",
		"gender": "Male",
		"address": "8766 Dorton Trail"
	},
	{
		"id": 58,
		"first_name": "Durant",
		"last_name": "McCaughren",
		"email": "dmccaughren1l@topsy.com",
		"gender": "Male",
		"address": "37995 Muir Point"
	},
	{
		"id": 59,
		"first_name": "Clay",
		"last_name": "Girth",
		"email": "cgirth1m@t-online.de",
		"gender": "Male",
		"address": "78 Delladonna Crossing"
	},
	{
		"id": 60,
		"first_name": "Cristen",
		"last_name": "Leed",
		"email": "cleed1n@cloudflare.com",
		"gender": "Female",
		"address": "2605 Washington Lane"
	},
	{
		"id": 61,
		"first_name": "Levi",
		"last_name": "Ransfield",
		"email": "lransfield1o@huffingtonpost.com",
		"gender": "Male",
		"address": "107 Shopko Plaza"
	},
	{
		"id": 62,
		"first_name": "Merrie",
		"last_name": "Jeannel",
		"email": "mjeannel1p@yelp.com",
		"gender": "Female",
		"address": "99468 Prentice Circle"
	},
	{
		"id": 63,
		"first_name": "Mallorie",
		"last_name": "Waycott",
		"email": "mwaycott1q@facebook.com",
		"gender": "Female",
		"address": "76692 Little Fleur Park"
	},
	{
		"id": 64,
		"first_name": "Bibi",
		"last_name": "Bringloe",
		"email": "bbringloe1r@youtu.be",
		"gender": "Female",
		"address": "35 Golden Leaf Drive"
	},
	{
		"id": 65,
		"first_name": "Damiano",
		"last_name": "Gethin",
		"email": "dgethin1s@technorati.com",
		"gender": "Male",
		"address": "99700 Mandrake Drive"
	},
	{
		"id": 66,
		"first_name": "Alli",
		"last_name": "Sheldrick",
		"email": "asheldrick1t@google.ru",
		"gender": "Female",
		"address": "47135 Bluestem Pass"
	},
	{
		"id": 67,
		"first_name": "Reina",
		"last_name": "Zanelli",
		"email": "rzanelli1u@yolasite.com",
		"gender": "Female",
		"address": "69871 American Center"
	},
	{
		"id": 68,
		"first_name": "Gertrudis",
		"last_name": "Chamberlen",
		"email": "gchamberlen1v@addthis.com",
		"gender": "Female",
		"address": "4 Pankratz Junction"
	},
	{
		"id": 69,
		"first_name": "Elwin",
		"last_name": "Corcoran",
		"email": "ecorcoran1w@about.com",
		"gender": "Genderqueer",
		"address": "915 Mesta Trail"
	},
	{
		"id": 70,
		"first_name": "Corinne",
		"last_name": "Ambridge",
		"email": "cambridge1x@spotify.com",
		"gender": "Female",
		"address": "5272 Heath Alley"
	},
	{
		"id": 71,
		"first_name": "Johan",
		"last_name": "Vacher",
		"email": "jvacher1y@bloglovin.com",
		"gender": "Male",
		"address": "2 Hovde Plaza"
	},
	{
		"id": 72,
		"first_name": "Zebedee",
		"last_name": "Nelthropp",
		"email": "znelthropp1z@amazon.co.uk",
		"gender": "Male",
		"address": "988 Lakeland Alley"
	},
	{
		"id": 73,
		"first_name": "Ervin",
		"last_name": "Rault",
		"email": "erault20@bbc.co.uk",
		"gender": "Male",
		"address": "52 Garrison Lane"
	},
	{
		"id": 74,
		"first_name": "Margeaux",
		"last_name": "Phipson",
		"email": "mphipson21@blog.com",
		"gender": "Female",
		"address": "1589 Sachtjen Junction"
	},
	{
		"id": 75,
		"first_name": "Renate",
		"last_name": "Roy",
		"email": "rroy22@symantec.com",
		"gender": "Female",
		"address": "6630 Katie Terrace"
	},
	{
		"id": 76,
		"first_name": "Halie",
		"last_name": "Shipley",
		"email": "hshipley23@spotify.com",
		"gender": "Female",
		"address": "4171 Esker Trail"
	},
	{
		"id": 77,
		"first_name": "Lian",
		"last_name": "Mooney",
		"email": "lmooney24@state.tx.us",
		"gender": "Female",
		"address": "98649 John Wall Lane"
	},
	{
		"id": 78,
		"first_name": "Irena",
		"last_name": "Lawtie",
		"email": "ilawtie25@forbes.com",
		"gender": "Female",
		"address": "52894 Dorton Center"
	},
	{
		"id": 79,
		"first_name": "Etheline",
		"last_name": "Moynham",
		"email": "emoynham26@answers.com",
		"gender": "Female",
		"address": "21 Union Hill"
	},
	{
		"id": 80,
		"first_name": "Pedro",
		"last_name": "Humble",
		"email": "phumble27@wikia.com",
		"gender": "Male",
		"address": "64 Harper Trail"
	},
	{
		"id": 81,
		"first_name": "Goldie",
		"last_name": "Norbury",
		"email": "gnorbury28@trellian.com",
		"gender": "Female",
		"address": "4120 Hoffman Court"
	},
	{
		"id": 82,
		"first_name": "Olivier",
		"last_name": "Rowling",
		"email": "orowling29@bigcartel.com",
		"gender": "Male",
		"address": "43392 Ridgeway Street"
	},
	{
		"id": 83,
		"first_name": "Symon",
		"last_name": "Armand",
		"email": "sarmand2a@theatlantic.com",
		"gender": "Male",
		"address": "80 Michigan Junction"
	},
	{
		"id": 84,
		"first_name": "Cordell",
		"last_name": "Boddy",
		"email": "cboddy2b@webmd.com",
		"gender": "Male",
		"address": "35 Portage Circle"
	},
	{
		"id": 85,
		"first_name": "Cameron",
		"last_name": "O'Gormley",
		"email": "cogormley2c@photobucket.com",
		"gender": "Male",
		"address": "7 Namekagon Hill"
	},
	{
		"id": 86,
		"first_name": "Temple",
		"last_name": "Ingilson",
		"email": "tingilson2d@imageshack.us",
		"gender": "Male",
		"address": "702 Larry Place"
	},
	{
		"id": 87,
		"first_name": "Amerigo",
		"last_name": "Cicconettii",
		"email": "acicconettii2e@myspace.com",
		"gender": "Male",
		"address": "13847 Dapin Junction"
	},
	{
		"id": 88,
		"first_name": "Marcelo",
		"last_name": "Dimitresco",
		"email": "mdimitresco2f@typepad.com",
		"gender": "Male",
		"address": "0932 Beilfuss Plaza"
	},
	{
		"id": 89,
		"first_name": "Munroe",
		"last_name": "Dadson",
		"email": "mdadson2g@google.ru",
		"gender": "Male",
		"address": "5658 Welch Place"
	},
	{
		"id": 90,
		"first_name": "Lanie",
		"last_name": "Langridge",
		"email": "llangridge2h@surveymonkey.com",
		"gender": "Male",
		"address": "395 Starling Center"
	},
	{
		"id": 91,
		"first_name": "Matthus",
		"last_name": "Wivell",
		"email": "mwivell2i@illinois.edu",
		"gender": "Male",
		"address": "706 Paget Parkway"
	},
	{
		"id": 92,
		"first_name": "Neille",
		"last_name": "Hanbidge",
		"email": "nhanbidge2j@marriott.com",
		"gender": "Female",
		"address": "82 Pleasure Street"
	},
	{
		"id": 93,
		"first_name": "Donny",
		"last_name": "Margett",
		"email": "dmargett2k@google.de",
		"gender": "Male",
		"address": "9 Eggendart Terrace"
	},
	{
		"id": 94,
		"first_name": "Daven",
		"last_name": "Yourell",
		"email": "dyourell2l@topsy.com",
		"gender": "Male",
		"address": "88 Monica Parkway"
	},
	{
		"id": 95,
		"first_name": "Carmine",
		"last_name": "Esh",
		"email": "cesh2m@mozilla.com",
		"gender": "Female",
		"address": "04606 Hagan Road"
	},
	{
		"id": 96,
		"first_name": "Livvy",
		"last_name": "Dominey",
		"email": "ldominey2n@china.com.cn",
		"gender": "Genderqueer",
		"address": "8 Blue Bill Park Junction"
	},
	{
		"id": 97,
		"first_name": "Bryant",
		"last_name": "Cawdell",
		"email": "bcawdell2o@dailymail.co.uk",
		"gender": "Male",
		"address": "44 Roxbury Point"
	},
	{
		"id": 98,
		"first_name": "Urbain",
		"last_name": "Nairne",
		"email": "unairne2p@time.com",
		"gender": "Male",
		"address": "5 Randy Hill"
	},
	{
		"id": 99,
		"first_name": "Lori",
		"last_name": "Chadburn",
		"email": "lchadburn2q@theglobeandmail.com",
		"gender": "Female",
		"address": "4 Northview Center"
	},
	{
		"id": 100,
		"first_name": "Curtice",
		"last_name": "Hurtic",
		"email": "churtic2r@berkeley.edu",
		"gender": "Male",
		"address": "5007 Pine View Way"
	}
]